djangocms_calameo/__init__.py
djangocms_calameo/cms_plugins.py
djangocms_calameo/locale/fr/LC_MESSAGES/django.mo
djangocms_calameo/locale/fr/LC_MESSAGES/django.po
djangocms_calameo/migrations/0001_initial.py
djangocms_calameo/migrations/__init__.py
djangocms_calameo/models.py
djangocms_calameo/templates/djangocms_calameo/default.html
djangocms_calameo-4.0.1.dist-info/LICENSE
djangocms_calameo-4.0.1.dist-info/METADATA
djangocms_calameo-4.0.1.dist-info/WHEEL
djangocms_calameo-4.0.1.dist-info/RECORD
