Metadata-Version: 2.1
Name: djangocms_calameo
Version: 4.0.1
Summary: Django CMS Calaméo is a plugin for Django CMS that allows you to add Calaméo widgets on your site.
Home-page: https://gitlab.com/kapt/open-source/djangocms-calameo
License: GPL-3.0-or-later
Author: Kapt dev team
Author-email: dev@kapt.mobi
Requires-Python: >=3.8
Classifier: License :: OSI Approved :: GNU General Public License v3 or later (GPLv3+)
Classifier: Programming Language :: Python :: 3
Classifier: Programming Language :: Python :: 3.8
Classifier: Programming Language :: Python :: 3.9
Classifier: Programming Language :: Python :: 3.10
Classifier: Programming Language :: Python :: 3.11
Requires-Dist: Django (>=1.11)
Requires-Dist: django-cms (>=3.8)
Project-URL: Repository, https://gitlab.com/kapt/open-source/djangocms-calameo
